README.txt
setup.cfg
setup.py
Products/__init__.py
Products.signalstackLogger.egg-info/PKG-INFO
Products.signalstackLogger.egg-info/SOURCES.txt
Products.signalstackLogger.egg-info/dependency_links.txt
Products.signalstackLogger.egg-info/namespace_packages.txt
Products.signalstackLogger.egg-info/not-zip-safe
Products.signalstackLogger.egg-info/requires.txt
Products.signalstackLogger.egg-info/top_level.txt
Products/signalstackLogger/__init__.py
Products/signalstackLogger/configure.zcml
docs/HISTORY.txt