Metadata-Version: 1.0
Name: Products.signalstackLogger
Version: 0.9
Summary: Output zope stacktrace on signal using logging facility
Home-page: UNKNOWN
Author: Andy Altepeter
Author-email: aaltepet@altepeter.net
License: BSD
Platform: UNKNOWN
Classifier: Framework :: Zope2
Classifier: Intended Audience :: Developers
Classifier: License :: OSI Approved :: BSD License
Classifier: Programming Language :: Python
Classifier: Topic :: Software Development :: Libraries :: Python Modules
